{"stats":{"minecraft:killed_by":{"minecraft:player":5},"minecraft:mined":{"minecraft:red_bed":2},"minecraft:used":{"minecraft:wooden_sword":16},"minecraft:crafted":{"minecraft:bone":2},"minecraft:dropped":{"minecraft:command_block":1,"minecraft:bone":2},"minecraft:picked_up":{"minecraft:command_block":1,"minecraft:diamond":4,"minecraft:iron_ingot":245,"minecraft:gold_ingot":7},"minecraft:custom":{"minecraft:time_since_rest":3262,"minecraft:open_chest":2,"minecraft:play_one_minute":18269,"minecraft:sprint_one_cm":23104,"minecraft:walk_one_cm":11524,"minecraft:damage_taken":1634,"minecraft:deaths":5,"minecraft:sneak_time":6,"minecraft:drop":3,"minecraft:jump":64,"minecraft:damage_dealt":781,"minecraft:leave_game":1,"minecraft:time_since_death":3262,"minecraft:traded_with_villager":2,"minecraft:climb_one_cm":330,"minecraft:damage_resisted":873,"minecraft:fall_one_cm":305,"minecraft:talked_to_villager":6,"minecraft:fly_one_cm":24563,"minecraft:player_kills":3}},"DataVersion":2586}